[
    {
        "date": "2024-05-24",
        "river_flow": 2407,
        "water_level": 4.5,
        "water_temperature": 68,
        "rapid_difficulty": "Class III",
        "recent_precipitation": 1.22,
        "river_condition": "High Risk"
    },
    {
        "date": "2024-05-25",
        "river_flow": 1507,
        "water_level": 2.87,
        "water_temperature": 55,
        "rapid_difficulty": "Class III",
        "recent_precipitation": 1.26,
        "river_condition": "High Risk"
    },
    {
        "date": "2024-05-26",
        "river_flow": 3256,
        "water_level": 4.0,
        "water_temperature": 73,
        "rapid_difficulty": "Class IV",
        "recent_precipitation": 1.07,
        "river_condition": "High Risk"
    },
    {
        "date": "2024-05-27",
        "river_flow": 850,
        "water_level": 3.62,
        "water_temperature": 66,
        "rapid_difficulty": "Class II",
        "recent_precipitation": 1.88,
        "river_condition": "High Risk"
    },
    {
        "date": "2024-05-28",
        "river_flow": 2561,
        "water_level": 2.9,
        "water_temperature": 68,
        "rapid_difficulty": "Class IV",
        "recent_precipitation": 1.77,
        "river_condition": "High Risk"
    },
    {
        "date": "2024-05-29",
        "river_flow": 3357,
        "water_level": 2.87,
        "water_temperature": 74,
        "rapid_difficulty": "Class IV",
        "recent_precipitation": 1.62,
        "river_condition": "High Risk"
    },
    {
        "date": "2024-05-30",
        "river_flow": 3418,
        "water_level": 5.76,
        "water_temperature": 63,
        "rapid_difficulty": "Class IV",
        "recent_precipitation": 0.54,
        "river_condition": "High Risk"
    },
    {
        "date": "2024-05-31",
        "river_flow": 2694,
        "water_level": 5.0,
        "water_temperature": 55,
        "rapid_difficulty": "Class IV",
        "recent_precipitation": 0.61,
        "river_condition": "Moderate Risk"
    },
    {
        "date": "2024-06-01",
        "river_flow": 1196,
        "water_level": 4.04,
        "water_temperature": 59,
        "rapid_difficulty": "Class III",
        "recent_precipitation": 1.27,
        "river_condition": "High Risk"
    },
    {
        "date": "2024-06-02",
        "river_flow": 2891,
        "water_level": 4.44,
        "water_temperature": 63,
        "rapid_difficulty": "Class IV",
        "recent_precipitation": 1.86,
        "river_condition": "High Risk"
    },
    {
        "date": "2024-06-03",
        "river_flow": 3422,
        "water_level": 5.6,
        "water_temperature": 70,
        "rapid_difficulty": "Class IV",
        "recent_precipitation": 0.05,
        "river_condition": "High Risk"
    },
    {
        "date": "2024-06-04",
        "river_flow": 1020,
        "water_level": 4.52,
        "water_temperature": 66,
        "rapid_difficulty": "Class III",
        "recent_precipitation": 0.0,
        "river_condition": "Safe"
    },
    {
        "date": "2024-06-05",
        "river_flow": 3181,
        "water_level": 2.94,
        "water_temperature": 72,
        "rapid_difficulty": "Class IV",
        "recent_precipitation": 0.29,
        "river_condition": "High Risk"
    },
    {
        "date": "2024-06-06",
        "river_flow": 2492,
        "water_level": 4.5,
        "water_temperature": 63,
        "rapid_difficulty": "Class III",
        "recent_precipitation": 0.71,
        "river_condition": "Moderate Risk"
    },
    {
        "date": "2024-06-07",
        "river_flow": 2118,
        "water_level": 3.06,
        "water_temperature": 67,
        "rapid_difficulty": "Class III",
        "recent_precipitation": 1.79,
        "river_condition": "High Risk"
    },
    {
        "date": "2024-06-08",
        "river_flow": 3243,
        "water_level": 4.76,
        "water_temperature": 69,
        "rapid_difficulty": "Class IV",
        "recent_precipitation": 1.93,
        "river_condition": "High Risk"
    },
    {
        "date": "2024-06-09",
        "river_flow": 3361,
        "water_level": 3.02,
        "water_temperature": 72,
        "rapid_difficulty": "Class IV",
        "recent_precipitation": 0.96,
        "river_condition": "High Risk"
    },
    {
        "date": "2024-06-10",
        "river_flow": 3409,
        "water_level": 2.67,
        "water_temperature": 71,
        "rapid_difficulty": "Class IV",
        "recent_precipitation": 0.31,
        "river_condition": "High Risk"
    },
    {
        "date": "2024-06-11",
        "river_flow": 2071,
        "water_level": 5.92,
        "water_temperature": 68,
        "rapid_difficulty": "Class III",
        "recent_precipitation": 1.82,
        "river_condition": "High Risk"
    },
    {
        "date": "2024-06-12",
        "river_flow": 1532,
        "water_level": 3.8,
        "water_temperature": 72,
        "rapid_difficulty": "Class III",
        "recent_precipitation": 1.15,
        "river_condition": "High Risk"
    },
    {
        "date": "2024-06-13",
        "river_flow": 1196,
        "water_level": 5.49,
        "water_temperature": 74,
        "rapid_difficulty": "Class III",
        "recent_precipitation": 1.9,
        "river_condition": "High Risk"
    },
    {
        "date": "2024-06-14",
        "river_flow": 1491,
        "water_level": 3.36,
        "water_temperature": 72,
        "rapid_difficulty": "Class III",
        "recent_precipitation": 1.61,
        "river_condition": "High Risk"
    },
    {
        "date": "2024-06-15",
        "river_flow": 2109,
        "water_level": 2.78,
        "water_temperature": 67,
        "rapid_difficulty": "Class III",
        "recent_precipitation": 1.99,
        "river_condition": "High Risk"
    },
    {
        "date": "2024-06-16",
        "river_flow": 930,
        "water_level": 3.46,
        "water_temperature": 70,
        "rapid_difficulty": "Class II",
        "recent_precipitation": 1.46,
        "river_condition": "High Risk"
    },
    {
        "date": "2024-06-17",
        "river_flow": 813,
        "water_level": 3.48,
        "water_temperature": 68,
        "rapid_difficulty": "Class II",
        "recent_precipitation": 0.42,
        "river_condition": "Safe"
    },
    {
        "date": "2024-06-18",
        "river_flow": 2628,
        "water_level": 4.61,
        "water_temperature": 55,
        "rapid_difficulty": "Class IV",
        "recent_precipitation": 0.02,
        "river_condition": "Moderate Risk"
    },
    {
        "date": "2024-06-19",
        "river_flow": 2229,
        "water_level": 3.13,
        "water_temperature": 66,
        "rapid_difficulty": "Class III",
        "recent_precipitation": 0.4,
        "river_condition": "Moderate Risk"
    },
    {
        "date": "2024-06-20",
        "river_flow": 1398,
        "water_level": 3.06,
        "water_temperature": 66,
        "rapid_difficulty": "Class III",
        "recent_precipitation": 1.5,
        "river_condition": "High Risk"
    },
    {
        "date": "2024-06-21",
        "river_flow": 2179,
        "water_level": 4.84,
        "water_temperature": 60,
        "rapid_difficulty": "Class III",
        "recent_precipitation": 1.01,
        "river_condition": "High Risk"
    },
    {
        "date": "2024-06-22",
        "river_flow": 2138,
        "water_level": 5.15,
        "water_temperature": 59,
        "rapid_difficulty": "Class III",
        "recent_precipitation": 1.34,
        "river_condition": "High Risk"
    },
    {
        "date": "2024-06-23",
        "river_flow": 3498,
        "water_level": 5.28,
        "water_temperature": 64,
        "rapid_difficulty": "Class IV",
        "recent_precipitation": 0.97,
        "river_condition": "High Risk"
    },
    {
        "date": "2024-06-24",
        "river_flow": 1201,
        "water_level": 2.86,
        "water_temperature": 70,
        "rapid_difficulty": "Class III",
        "recent_precipitation": 0.93,
        "river_condition": "Safe"
    },
    {
        "date": "2024-06-25",
        "river_flow": 1756,
        "water_level": 4.3,
        "water_temperature": 68,
        "rapid_difficulty": "Class III",
        "recent_precipitation": 0.53,
        "river_condition": "Safe"
    },
    {
        "date": "2024-06-26",
        "river_flow": 2990,
        "water_level": 4.55,
        "water_temperature": 58,
        "rapid_difficulty": "Class IV",
        "recent_precipitation": 1.76,
        "river_condition": "High Risk"
    },
    {
        "date": "2024-06-27",
        "river_flow": 3434,
        "water_level": 5.06,
        "water_temperature": 73,
        "rapid_difficulty": "Class IV",
        "recent_precipitation": 0.13,
        "river_condition": "High Risk"
    },
    {
        "date": "2024-06-28",
        "river_flow": 1601,
        "water_level": 3.32,
        "water_temperature": 61,
        "rapid_difficulty": "Class III",
        "recent_precipitation": 0.99,
        "river_condition": "Safe"
    },
    {
        "date": "2024-06-29",
        "river_flow": 1467,
        "water_level": 3.79,
        "water_temperature": 65,
        "rapid_difficulty": "Class III",
        "recent_precipitation": 1.12,
        "river_condition": "High Risk"
    },
    {
        "date": "2024-06-30",
        "river_flow": 2940,
        "water_level": 4.4,
        "water_temperature": 70,
        "rapid_difficulty": "Class IV",
        "recent_precipitation": 0.9,
        "river_condition": "Moderate Risk"
    },
    {
        "date": "2024-07-01",
        "river_flow": 2236,
        "water_level": 4.0,
        "water_temperature": 63,
        "rapid_difficulty": "Class III",
        "recent_precipitation": 1.58,
        "river_condition": "High Risk"
    },
    {
        "date": "2024-07-02",
        "river_flow": 3050,
        "water_level": 2.8,
        "water_temperature": 69,
        "rapid_difficulty": "Class IV",
        "recent_precipitation": 0.07,
        "river_condition": "High Risk"
    },
    {
        "date": "2024-07-03",
        "river_flow": 2220,
        "water_level": 5.24,
        "water_temperature": 70,
        "rapid_difficulty": "Class III",
        "recent_precipitation": 0.19,
        "river_condition": "Moderate Risk"
    },
    {
        "date": "2024-07-04",
        "river_flow": 992,
        "water_level": 5.81,
        "water_temperature": 57,
        "rapid_difficulty": "Class II",
        "recent_precipitation": 1.2,
        "river_condition": "High Risk"
    },
    {
        "date": "2024-07-05",
        "river_flow": 1402,
        "water_level": 3.2,
        "water_temperature": 74,
        "rapid_difficulty": "Class III",
        "recent_precipitation": 1.23,
        "river_condition": "High Risk"
    },
    {
        "date": "2024-07-06",
        "river_flow": 1373,
        "water_level": 3.37,
        "water_temperature": 56,
        "rapid_difficulty": "Class III",
        "recent_precipitation": 0.09,
        "river_condition": "Safe"
    },
    {
        "date": "2024-07-07",
        "river_flow": 2117,
        "water_level": 2.62,
        "water_temperature": 72,
        "rapid_difficulty": "Class III",
        "recent_precipitation": 0.24,
        "river_condition": "Moderate Risk"
    },
    {
        "date": "2024-07-08",
        "river_flow": 1836,
        "water_level": 4.27,
        "water_temperature": 58,
        "rapid_difficulty": "Class III",
        "recent_precipitation": 0.48,
        "river_condition": "Safe"
    },
    {
        "date": "2024-07-09",
        "river_flow": 2170,
        "water_level": 3.2,
        "water_temperature": 60,
        "rapid_difficulty": "Class III",
        "recent_precipitation": 1.42,
        "river_condition": "High Risk"
    },
    {
        "date": "2024-07-10",
        "river_flow": 1012,
        "water_level": 5.92,
        "water_temperature": 65,
        "rapid_difficulty": "Class III",
        "recent_precipitation": 0.94,
        "river_condition": "Safe"
    },
    {
        "date": "2024-07-11",
        "river_flow": 1445,
        "water_level": 2.75,
        "water_temperature": 70,
        "rapid_difficulty": "Class III",
        "recent_precipitation": 1.86,
        "river_condition": "High Risk"
    },
    {
        "date": "2024-07-12",
        "river_flow": 3001,
        "water_level": 4.51,
        "water_temperature": 66,
        "rapid_difficulty": "Class IV",
        "recent_precipitation": 1.93,
        "river_condition": "High Risk"
    },
    {
        "date": "2024-07-13",
        "river_flow": 2394,
        "water_level": 3.59,
        "water_temperature": 63,
        "rapid_difficulty": "Class III",
        "recent_precipitation": 0.77,
        "river_condition": "Moderate Risk"
    },
    {
        "date": "2024-07-14",
        "river_flow": 2096,
        "water_level": 5.99,
        "water_temperature": 74,
        "rapid_difficulty": "Class III",
        "recent_precipitation": 1.85,
        "river_condition": "High Risk"
    },
    {
        "date": "2024-07-15",
        "river_flow": 2365,
        "water_level": 5.95,
        "water_temperature": 68,
        "rapid_difficulty": "Class III",
        "recent_precipitation": 1.36,
        "river_condition": "High Risk"
    },
    {
        "date": "2024-07-16",
        "river_flow": 838,
        "water_level": 5.46,
        "water_temperature": 58,
        "rapid_difficulty": "Class II",
        "recent_precipitation": 1.51,
        "river_condition": "High Risk"
    },
    {
        "date": "2024-07-17",
        "river_flow": 3141,
        "water_level": 5.36,
        "water_temperature": 56,
        "rapid_difficulty": "Class IV",
        "recent_precipitation": 1.33,
        "river_condition": "High Risk"
    },
    {
        "date": "2024-07-18",
        "river_flow": 3373,
        "water_level": 2.5,
        "water_temperature": 66,
        "rapid_difficulty": "Class IV",
        "recent_precipitation": 0.62,
        "river_condition": "High Risk"
    },
    {
        "date": "2024-07-19",
        "river_flow": 2284,
        "water_level": 3.42,
        "water_temperature": 70,
        "rapid_difficulty": "Class III",
        "recent_precipitation": 0.53,
        "river_condition": "Moderate Risk"
    },
    {
        "date": "2024-07-20",
        "river_flow": 1967,
        "water_level": 5.44,
        "water_temperature": 74,
        "rapid_difficulty": "Class III",
        "recent_precipitation": 0.45,
        "river_condition": "Safe"
    },
    {
        "date": "2024-07-21",
        "river_flow": 2226,
        "water_level": 5.32,
        "water_temperature": 61,
        "rapid_difficulty": "Class III",
        "recent_precipitation": 0.63,
        "river_condition": "Moderate Risk"
    },
    {
        "date": "2024-07-22",
        "river_flow": 3228,
        "water_level": 2.6,
        "water_temperature": 67,
        "rapid_difficulty": "Class IV",
        "recent_precipitation": 0.85,
        "river_condition": "High Risk"
    },
    {
        "date": "2024-07-23",
        "river_flow": 3046,
        "water_level": 3.6,
        "water_temperature": 72,
        "rapid_difficulty": "Class IV",
        "recent_precipitation": 0.53,
        "river_condition": "High Risk"
    },
    {
        "date": "2024-07-24",
        "river_flow": 1595,
        "water_level": 3.14,
        "water_temperature": 70,
        "rapid_difficulty": "Class III",
        "recent_precipitation": 1.69,
        "river_condition": "High Risk"
    },
    {
        "date": "2024-07-25",
        "river_flow": 1080,
        "water_level": 3.5,
        "water_temperature": 75,
        "rapid_difficulty": "Class III",
        "recent_precipitation": 0.25,
        "river_condition": "Safe"
    },
    {
        "date": "2024-07-26",
        "river_flow": 1327,
        "water_level": 2.8,
        "water_temperature": 71,
        "rapid_difficulty": "Class III",
        "recent_precipitation": 0.9,
        "river_condition": "Safe"
    },
    {
        "date": "2024-07-27",
        "river_flow": 1497,
        "water_level": 3.78,
        "water_temperature": 58,
        "rapid_difficulty": "Class III",
        "recent_precipitation": 0.9,
        "river_condition": "Safe"
    },
    {
        "date": "2024-07-28",
        "river_flow": 2749,
        "water_level": 5.14,
        "water_temperature": 60,
        "rapid_difficulty": "Class IV",
        "recent_precipitation": 1.59,
        "river_condition": "High Risk"
    },
    {
        "date": "2024-07-29",
        "river_flow": 1187,
        "water_level": 4.36,
        "water_temperature": 71,
        "rapid_difficulty": "Class III",
        "recent_precipitation": 1.38,
        "river_condition": "High Risk"
    },
    {
        "date": "2024-07-30",
        "river_flow": 1149,
        "water_level": 3.97,
        "water_temperature": 67,
        "rapid_difficulty": "Class III",
        "recent_precipitation": 1.09,
        "river_condition": "High Risk"
    },
    {
        "date": "2024-07-31",
        "river_flow": 2545,
        "water_level": 3.55,
        "water_temperature": 56,
        "rapid_difficulty": "Class IV",
        "recent_precipitation": 0.57,
        "river_condition": "Moderate Risk"
    },
    {
        "date": "2024-08-01",
        "river_flow": 1397,
        "water_level": 3.33,
        "water_temperature": 72,
        "rapid_difficulty": "Class III",
        "recent_precipitation": 1.67,
        "river_condition": "High Risk"
    },
    {
        "date": "2024-08-02",
        "river_flow": 2068,
        "water_level": 4.83,
        "water_temperature": 69,
        "rapid_difficulty": "Class III",
        "recent_precipitation": 1.04,
        "river_condition": "High Risk"
    },
    {
        "date": "2024-08-03",
        "river_flow": 2261,
        "water_level": 5.57,
        "water_temperature": 65,
        "rapid_difficulty": "Class III",
        "recent_precipitation": 0.9,
        "river_condition": "Moderate Risk"
    },
    {
        "date": "2024-08-04",
        "river_flow": 1562,
        "water_level": 3.73,
        "water_temperature": 70,
        "rapid_difficulty": "Class III",
        "recent_precipitation": 1.17,
        "river_condition": "High Risk"
    },
    {
        "date": "2024-08-05",
        "river_flow": 2932,
        "water_level": 3.88,
        "water_temperature": 71,
        "rapid_difficulty": "Class IV",
        "recent_precipitation": 0.67,
        "river_condition": "Moderate Risk"
    },
    {
        "date": "2024-08-06",
        "river_flow": 2347,
        "water_level": 3.93,
        "water_temperature": 61,
        "rapid_difficulty": "Class III",
        "recent_precipitation": 1.15,
        "river_condition": "High Risk"
    },
    {
        "date": "2024-08-07",
        "river_flow": 1818,
        "water_level": 3.1,
        "water_temperature": 66,
        "rapid_difficulty": "Class III",
        "recent_precipitation": 1.6,
        "river_condition": "High Risk"
    },
    {
        "date": "2024-08-08",
        "river_flow": 3076,
        "water_level": 2.78,
        "water_temperature": 74,
        "rapid_difficulty": "Class IV",
        "recent_precipitation": 0.36,
        "river_condition": "High Risk"
    },
    {
        "date": "2024-08-09",
        "river_flow": 1087,
        "water_level": 4.05,
        "water_temperature": 70,
        "rapid_difficulty": "Class III",
        "recent_precipitation": 1.98,
        "river_condition": "High Risk"
    },
    {
        "date": "2024-08-10",
        "river_flow": 3407,
        "water_level": 3.28,
        "water_temperature": 63,
        "rapid_difficulty": "Class IV",
        "recent_precipitation": 0.96,
        "river_condition": "High Risk"
    },
    {
        "date": "2024-08-11",
        "river_flow": 2891,
        "water_level": 4.07,
        "water_temperature": 59,
        "rapid_difficulty": "Class IV",
        "recent_precipitation": 1.7,
        "river_condition": "High Risk"
    },
    {
        "date": "2024-08-12",
        "river_flow": 3151,
        "water_level": 5.74,
        "water_temperature": 57,
        "rapid_difficulty": "Class IV",
        "recent_precipitation": 0.78,
        "river_condition": "High Risk"
    },
    {
        "date": "2024-08-13",
        "river_flow": 976,
        "water_level": 5.39,
        "water_temperature": 73,
        "rapid_difficulty": "Class II",
        "recent_precipitation": 1.1,
        "river_condition": "High Risk"
    },
    {
        "date": "2024-08-14",
        "river_flow": 861,
        "water_level": 4.03,
        "water_temperature": 69,
        "rapid_difficulty": "Class II",
        "recent_precipitation": 1.83,
        "river_condition": "High Risk"
    },
    {
        "date": "2024-08-15",
        "river_flow": 1207,
        "water_level": 5.78,
        "water_temperature": 75,
        "rapid_difficulty": "Class III",
        "recent_precipitation": 1.19,
        "river_condition": "High Risk"
    },
    {
        "date": "2024-08-16",
        "river_flow": 1336,
        "water_level": 5.47,
        "water_temperature": 56,
        "rapid_difficulty": "Class III",
        "recent_precipitation": 0.38,
        "river_condition": "Safe"
    },
    {
        "date": "2024-08-17",
        "river_flow": 2464,
        "water_level": 3.23,
        "water_temperature": 57,
        "rapid_difficulty": "Class III",
        "recent_precipitation": 0.8,
        "river_condition": "Moderate Risk"
    },
    {
        "date": "2024-08-18",
        "river_flow": 2192,
        "water_level": 4.16,
        "water_temperature": 62,
        "rapid_difficulty": "Class III",
        "recent_precipitation": 0.09,
        "river_condition": "Moderate Risk"
    },
    {
        "date": "2024-08-19",
        "river_flow": 1911,
        "water_level": 3.96,
        "water_temperature": 67,
        "rapid_difficulty": "Class III",
        "recent_precipitation": 0.69,
        "river_condition": "Safe"
    },
    {
        "date": "2024-08-20",
        "river_flow": 3378,
        "water_level": 5.91,
        "water_temperature": 59,
        "rapid_difficulty": "Class IV",
        "recent_precipitation": 1.34,
        "river_condition": "High Risk"
    },
    {
        "date": "2024-08-21",
        "river_flow": 2530,
        "water_level": 3.44,
        "water_temperature": 56,
        "rapid_difficulty": "Class IV",
        "recent_precipitation": 1.21,
        "river_condition": "High Risk"
    },
    {
        "date": "2024-08-22",
        "river_flow": 1041,
        "water_level": 5.54,
        "water_temperature": 64,
        "rapid_difficulty": "Class III",
        "recent_precipitation": 1.61,
        "river_condition": "High Risk"
    },
    {
        "date": "2024-08-23",
        "river_flow": 3130,
        "water_level": 2.88,
        "water_temperature": 62,
        "rapid_difficulty": "Class IV",
        "recent_precipitation": 0.49,
        "river_condition": "High Risk"
    },
    {
        "date": "2024-08-24",
        "river_flow": 1607,
        "water_level": 5.25,
        "water_temperature": 62,
        "rapid_difficulty": "Class III",
        "recent_precipitation": 0.98,
        "river_condition": "Safe"
    },
    {
        "date": "2024-08-25",
        "river_flow": 1219,
        "water_level": 2.66,
        "water_temperature": 73,
        "rapid_difficulty": "Class III",
        "recent_precipitation": 1.0,
        "river_condition": "Safe"
    },
    {
        "date": "2024-08-26",
        "river_flow": 2450,
        "water_level": 4.81,
        "water_temperature": 72,
        "rapid_difficulty": "Class III",
        "recent_precipitation": 1.84,
        "river_condition": "High Risk"
    },
    {
        "date": "2024-08-27",
        "river_flow": 1509,
        "water_level": 4.79,
        "water_temperature": 59,
        "rapid_difficulty": "Class III",
        "recent_precipitation": 0.33,
        "river_condition": "Safe"
    },
    {
        "date": "2024-08-28",
        "river_flow": 1653,
        "water_level": 3.8,
        "water_temperature": 70,
        "rapid_difficulty": "Class III",
        "recent_precipitation": 1.45,
        "river_condition": "High Risk"
    },
    {
        "date": "2024-08-29",
        "river_flow": 1016,
        "water_level": 5.04,
        "water_temperature": 65,
        "rapid_difficulty": "Class III",
        "recent_precipitation": 0.55,
        "river_condition": "Safe"
    },
    {
        "date": "2024-08-30",
        "river_flow": 1712,
        "water_level": 4.43,
        "water_temperature": 73,
        "rapid_difficulty": "Class III",
        "recent_precipitation": 1.07,
        "river_condition": "High Risk"
    },
    {
        "date": "2024-08-31",
        "river_flow": 2282,
        "water_level": 5.05,
        "water_temperature": 74,
        "rapid_difficulty": "Class III",
        "recent_precipitation": 0.38,
        "river_condition": "Moderate Risk"
    },
    {
        "date": "2024-09-01",
        "river_flow": 2033,
        "water_level": 3.66,
        "water_temperature": 67,
        "rapid_difficulty": "Class III",
        "recent_precipitation": 1.87,
        "river_condition": "High Risk"
    },
    {
        "date": "2024-09-02",
        "river_flow": 2955,
        "water_level": 5.33,
        "water_temperature": 66,
        "rapid_difficulty": "Class IV",
        "recent_precipitation": 1.28,
        "river_condition": "High Risk"
    }
]